backupdirs3/__init__.py
backupdirs3/main.py
backupdirs3-0.3.10.dist-info/LICENSE
backupdirs3-0.3.10.dist-info/METADATA
backupdirs3-0.3.10.dist-info/WHEEL
backupdirs3-0.3.10.dist-info/entry_points.txt
backupdirs3-0.3.10.dist-info/RECORD
