Metadata-Version: 2.1
Name: backupdirs3
Version: 0.3.10
Summary: This tool monitors a directory for changes, create a backup in the form of a zip file, and upload it to an AWS S3 bucket.
Home-page: https://github.com/ludenus/backupdirs3
License: MIT
Keywords: backup,aws,s3,directory-monitor
Author: Andrey Andreyev
Author-email: x0153362@gmail.com
Requires-Python: >=3.10,<4.0
Classifier: License :: OSI Approved :: MIT License
Classifier: Operating System :: POSIX :: Linux
Classifier: Programming Language :: Python :: 3
Classifier: Programming Language :: Python :: 3.10
Classifier: Programming Language :: Python :: 3.11
Classifier: Programming Language :: Python :: 3.12
Requires-Dist: boto3 (>=1.35.18,<2.0.0)
Requires-Dist: inotify (>=0.2.10,<0.3.0)
Requires-Dist: pyyaml (>=6.0.2,<7.0.0)
Project-URL: Documentation, https://github.com/ludenus/backupdirs3
Project-URL: Repository, https://github.com/ludenus/backupdirs3
